Workbook

Sheet Instructions
A1: ResumeBuilder AI — Detailed Financial Model (500 Users)
A3: How to use:
A4: 1) Go to the Inputs sheet and edit the yellow cells (assumptions).
A5: 2) Choose a scenario in Inputs!B6 (Conservative / Base / Aggressive).
A6: 3) Review the Monthly Forecast, Unit Economics, and Sensitivity sheets.
A7: 4) Recommendations sheet includes practical targets and next experiments.
A9: Model notes:
A10: • This model assumes monthly conversion rates apply to MAU for each month (simple, planning-grade).
A11: • Subscription churn is used for LTV estimates (job-seeker churn is naturally high).
A12: • AI cost is based on tokens = MAU × tailors/user × tokens/tailor; adjust token assumptions for your prompt design.
A14: Last updated: 2026-01-18

Sheet Scenarios
A1: Scenario | B1: Sub Conversion | C1: One-Time Conversion | D1: Monthly Sub Churn | E1: Notes
A2: Conservative | B2: 0.07 | C2: 0.03 | D2: 0.18 | E2: Lower conversion, higher churn
A3: Base | B3: 0.15 | C3: 0.05 | D3: 0.12 | E3: Balanced / realistic starting point
A4: Aggressive | B4: 0.25 | C4: 0.08 | D4: 0.1 | E4: Strong product-market fit + good activation

Sheet Inputs
A1: Editable Inputs (yellow)
A3: Scenario | B3: Base | C3: Select a scenario; conversion & churn auto-fill from Scenarios sheet.
A5: Category | B5: Metric | C5: Value | D5: Units | E5: Notes
A6: Users | B6: Monthly Active Users (MAU) | C6: 500 | D6: users | E6: Planning baseline
A7: Users | B7: Monthly MAU growth | C7: 0 | D7: % | E7: Set >0 if you expect growth
A8: Usage | B8: Tailors (or exports) per active user / month | C8: 1.5 | D8: count | E8: Avg across all users
A9: Usage | B9: Tokens per tailor (prompt+output) | C9: 30000 | D9: tokens | E9: Adjust based on your prompt length/output
A10: Pricing | B10: Subscription price | C10: 19 | D10: USD | E10: Monthly job-seeker plan
A11: Pricing | B11: One-time price | C11: 9 | D11: USD | E11: Per export/tailor
A12: Costs | B12: AI cost per 1M tokens | C12: 3 | D12: USD | E12: Put your real model blended cost here
A13: Costs | B13: Infrastructure & tools (fixed) | C13: 250 | D13: USD/mo | E13: Vercel + Supabase + email + monitoring
A14: Costs | B14: Support hours / month | C14: 15 | D14: hours | E14: Includes maintenance + prompt tuning
A15: Costs | B15: Fully-loaded hourly cost | C15: 30 | D15: USD/hr | E15: Valuation even if founder time
A16: Costs | B16: Marketing spend | C16: 750 | D16: USD/mo | E16: Cash spend (set 0 if organic)
A17: Costs | B17: Accounting & misc buffer | C17: 75 | D17: USD/mo | E17: Bookkeeping, refunds buffer, misc tools
... A20: Risk | B20: Refunds/chargebacks rate | C20: 0.01 | D20: % | E20: Conservative buffer
A22: Auto-filled from Scenario | B22: Metric | C22: Value | D22: Units | E22: Formula
A23: Scenario | B23: Subscription conversion | C23: =INDEX(Scenarios!B:B, MATCH($B$3, Scenarios!A:A, 0)) -> 0.15 | D23: % | E23: =INDEX(Scenarios!B:B, MATCH($B$3, Scenarios!A:A, 0)) -> 0.15
A24: Scenario | B24: One-time conversion | C24: =INDEX(Scenarios!C:C, MATCH($B$3, Scenarios!A:A, 0)) -> 0.05 | D24: % | E24: =INDEX(Scenarios!C:C, MATCH($B$3, Scenarios!A:A, 0)) -> 0.05
A25: Scenario | B25: Monthly subscription churn | C25: =INDEX(Scenarios!D:D, MATCH($B$3, Scenarios!A:A, 0)) -> 0.12 | D25: % | E25: =INDEX(Scenarios!D:D, MATCH($B$3, Scenarios!A:A, 0)) -> 0.12

Sheet Monthly Forecast
A1: 12-Month Forecast
A2: Month | B2: MAU | C2: Subscribers | D2: One-time Buyers | E2: Tailors | F2: Tokens | G2: Sub Revenue | H2: One-time Revenue | I2: Gross Revenue | J2: Refunds | K2: Net Revenue | L2: AI Cost | M2: Infra & Tools | N2: Support Cost | O2: Marketing | P2: Accounting/Misc | Q2: Payment Fees | R2: Total Costs | S2: Operating Profit
A3: 1 | B3: =Inputs!C6 -> 500 | C3: =B3*Inputs!C23 -> 75 | D3: =(B3-C3)*Inputs!C24 -> 21.25 | E3: =B3*Inputs!C8 -> 750 | F3: =E3*Inputs!C9 -> 22500000 | G3: =C3*Inputs!C10 -> 1425 | H3: =D3*Inputs!C11 -> 191.25 | I3: =G3+H3 -> 1616.25 | J3: =I3*Inputs!C20 -> 16.1625 | K3: =I3-J3 -> 1600.0875 | L3: =(F3/1000000)*Inputs!C12 -> 67.5 | M3: =Inputs!C13 -> 250 | N3: =Inputs!C14*Inputs!C15 -> 450 | O3: =Inputs!C16 -> 750 | P3: =Inputs!C17 -> 75 | Q3: =(K3*Inputs!C18) + ((C3+D3)*Inputs!C19) -> 76.877625 | R3: =L3+M3+N3+O3+P3+Q3 -> 1669.3776 | S3: =K3-R3 -> -69.290125
A4: 2 | B4: =B3*(1+Inputs!C7) -> 500 | C4: =B4*Inputs!C23 -> 75 | D4: =(B4-C4)*Inputs!C24 -> 21.25 | E4: =B4*Inputs!C8 -> 750 | F4: =E4*Inputs!C9 -> 22500000 | G4: =C4*Inputs!C10 -> 1425 | H4: =D4*Inputs!C11 -> 191.25 | I4: =G4+H4 -> 1616.25 | J4: =I4*Inputs!C20 -> 16.1625 | K4: =I4-J4 -> 1600.0875 | L4: =(F4/1000000)*Inputs!C12 -> 67.5 | M4: =Inputs!C13 -> 250 | N4: =Inputs!C14*Inputs!C15 -> 450 | O4: =Inputs!C16 -> 750 | P4: =Inputs!C17 -> 75 | Q4: =(K4*Inputs!C18) + ((C4+D4)*Inputs!C19) -> 76.877625 | R4: =L4+M4+N4+O4+P4+Q4 -> 1669.3776 | S4: =K4-R4 -> -69.290125
A5: 3 | B5: =B4*(1+Inputs!C7) -> 500 | C5: =B5*Inputs!C23 -> 75 | D5: =(B5-C5)*Inputs!C24 -> 21.25 | E5: =B5*Inputs!C8 -> 750 | F5: =E5*Inputs!C9 -> 22500000 | G5: =C5*Inputs!C10 -> 1425 | H5: =D5*Inputs!C11 -> 191.25 | I5: =G5+H5 -> 1616.25 | J5: =I5*Inputs!C20 -> 16.1625 | K5: =I5-J5 -> 1600.0875 | L5: =(F5/1000000)*Inputs!C12 -> 67.5 | M5: =Inputs!C13 -> 250 | N5: =Inputs!C14*Inputs!C15 -> 450 | O5: =Inputs!C16 -> 750 | P5: =Inputs!C17 -> 75 | Q5: =(K5*Inputs!C18) + ((C5+D5)*Inputs!C19) -> 76.877625 | R5: =L5+M5+N5+O5+P5+Q5 -> 1669.3776 | S5: =K5-R5 -> -69.290125
A6: 4 | B6: =B5*(1+Inputs!C7) -> 500 | C6: =B6*Inputs!C23 -> 75 | D6: =(B6-C6)*Inputs!C24 -> 21.25 | E6: =B6*Inputs!C8 -> 750 | F6: =E6*Inputs!C9 -> 22500000 | G6: =C6*Inputs!C10 -> 1425 | H6: =D6*Inputs!C11 -> 191.25 | I6: =G6+H6 -> 1616.25 | J6: =I6*Inputs!C20 -> 16.1625 | K6: =I6-J6 -> 1600.0875 | L6: =(F6/1000000)*Inputs!C12 -> 67.5 | M6: =Inputs!C13 -> 250 | N6: =Inputs!C14*Inputs!C15 -> 450 | O6: =Inputs!C16 -> 750 | P6: =Inputs!C17 -> 75 | Q6: =(K6*Inputs!C18) + ((C6+D6)*Inputs!C19) -> 76.877625 | R6: =L6+M6+N6+O6+P6+Q6 -> 1669.3776 | S6: =K6-R6 -> -69.290125
A7: 5 | B7: =B6*(1+Inputs!C7) -> 500 | C7: =B7*Inputs!C23 -> 75 | D7: =(B7-C7)*Inputs!C24 -> 21.25 | E7: =B7*Inputs!C8 -> 750 | F7: =E7*Inputs!C9 -> 22500000 | G7: =C7*Inputs!C10 -> 1425 | H7: =D7*Inputs!C11 -> 191.25 | I7: =G7+H7 -> 1616.25 | J7: =I7*Inputs!C20 -> 16.1625 | K7: =I7-J7 -> 1600.0875 | L7: =(F7/1000000)*Inputs!C12 -> 67.5 | M7: =Inputs!C13 -> 250 | N7: =Inputs!C14*Inputs!C15 -> 450 | O7: =Inputs!C16 -> 750 | P7: =Inputs!C17 -> 75 | Q7: =(K7*Inputs!C18) + ((C7+D7)*Inputs!C19) -> 76.877625 | R7: =L7+M7+N7+O7+P7+Q7 -> 1669.3776 | S7: =K7-R7 -> -69.290125
A8: 6 | B8: =B7*(1+Inputs!C7) -> 500 | C8: =B8*Inputs!C23 -> 75 | D8: =(B8-C8)*Inputs!C24 -> 21.25 | E8: =B8*Inputs!C8 -> 750 | F8: =E8*Inputs!C9 -> 22500000 | G8: =C8*Inputs!C10 -> 1425 | H8: =D8*Inputs!C11 -> 191.25 | I8: =G8+H8 -> 1616.25 | J8: =I8*Inputs!C20 -> 16.1625 | K8: =I8-J8 -> 1600.0875 | L8: =(F8/1000000)*Inputs!C12 -> 67.5 | M8: =Inputs!C13 -> 250 | N8: =Inputs!C14*Inputs!C15 -> 450 | O8: =Inputs!C16 -> 750 | P8: =Inputs!C17 -> 75 | Q8: =(K8*Inputs!C18) + ((C8+D8)*Inputs!C19) -> 76.877625 | R8: =L8+M8+N8+O8+P8+Q8 -> 1669.3776 | S8: =K8-R8 -> -69.290125
A9: 7 | B9: =B8*(1+Inputs!C7) -> 500 | C9: =B9*Inputs!C23 -> 75 | D9: =(B9-C9)*Inputs!C24 -> 21.25 | E9: =B9*Inputs!C8 -> 750 | F9: =E9*Inputs!C9 -> 22500000 | G9: =C9*Inputs!C10 -> 1425 | H9: =D9*Inputs!C11 -> 191.25 | I9: =G9+H9 -> 1616.25 | J9: =I9*Inputs!C20 -> 16.1625 | K9: =I9-J9 -> 1600.0875 | L9: =(F9/1000000)*Inputs!C12 -> 67.5 | M9: =Inputs!C13 -> 250 | N9: =Inputs!C14*Inputs!C15 -> 450 | O9: =Inputs!C16 -> 750 | P9: =Inputs!C17 -> 75 | Q9: =(K9*Inputs!C18) + ((C9+D9)*Inputs!C19) -> 76.877625 | R9: =L9+M9+N9+O9+P9+Q9 -> 1669.3776 | S9: =K9-R9 -> -69.290125
A10: 8 | B10: =B9*(1+Inputs!C7) -> 500 | C10: =B10*Inputs!C23 -> 75 | D10: =(B10-C10)*Inputs!C24 -> 21.25 | E10: =B10*Inputs!C8 -> 750 | F10: =E10*Inputs!C9 -> 22500000 | G10: =C10*Inputs!C10 -> 1425 | H10: =D10*Inputs!C11 -> 191.25 | I10: =G10+H10 -> 1616.25 | J10: =I10*Inputs!C20 -> 16.1625 | K10: =I10-J10 -> 1600.0875 | L10: =(F10/1000000)*Inputs!C12 -> 67.5 | M10: =Inputs!C13 -> 250 | N10: =Inputs!C14*Inputs!C15 -> 450 | O10: =Inputs!C16 -> 750 | P10: =Inputs!C17 -> 75 | Q10: =(K10*Inputs!C18) + ((C10+D10)*Inputs!C19) -> 76.877625 | R10: =L10+M10+N10+O10+P10+Q10 -> 1669.3776 | S10: =K10-R10 -> -69.290125
A11: 9 | B11: =B10*(1+Inputs!C7) -> 500 | C11: =B11*Inputs!C23 -> 75 | D11: =(B11-C11)*Inputs!C24 -> 21.25 | E11: =B11*Inputs!C8 -> 750 | F11: =E11*Inputs!C9 -> 22500000 | G11: =C11*Inputs!C10 -> 1425 | H11: =D11*Inputs!C11 -> 191.25 | I11: =G11+H11 -> 1616.25 | J11: =I11*Inputs!C20 -> 16.1625 | K11: =I11-J11 -> 1600.0875 | L11: =(F11/1000000)*Inputs!C12 -> 67.5 | M11: =Inputs!C13 -> 250 | N11: =Inputs!C14*Inputs!C15 -> 450 | O11: =Inputs!C16 -> 750 | P11: =Inputs!C17 -> 75 | Q11: =(K11*Inputs!C18) + ((C11+D11)*Inputs!C19) -> 76.877625 | R11: =L11+M11+N11+O11+P11+Q11 -> 1669.3776 | S11: =K11-R11 -> -69.290125
A12: 10 | B12: =B11*(1+Inputs!C7) -> 500 | C12: =B12*Inputs!C23 -> 75 | D12: =(B12-C12)*Inputs!C24 -> 21.25 | E12: =B12*Inputs!C8 -> 750 | F12: =E12*Inputs!C9 -> 22500000 | G12: =C12*Inputs!C10 -> 1425 | H12: =D12*Inputs!C11 -> 191.25 | I12: =G12+H12 -> 1616.25 | J12: =I12*Inputs!C20 -> 16.1625 | K12: =I12-J12 -> 1600.0875 | L12: =(F12/1000000)*Inputs!C12 -> 67.5 | M12: =Inputs!C13 -> 250 | N12: =Inputs!C14*Inputs!C15 -> 450 | O12: =Inputs!C16 -> 750 | P12: =Inputs!C17 -> 75 | Q12: =(K12*Inputs!C18) + ((C12+D12)*Inputs!C19) -> 76.877625 | R12: =L12+M12+N12+O12+P12+Q12 -> 1669.3776 | S12: =K12-R12 -> -69.290125
A13: 11 | B13: =B12*(1+Inputs!C7) -> 500 | C13: =B13*Inputs!C23 -> 75 | D13: =(B13-C13)*Inputs!C24 -> 21.25 | E13: =B13*Inputs!C8 -> 750 | F13: =E13*Inputs!C9 -> 22500000 | G13: =C13*Inputs!C10 -> 1425 | H13: =D13*Inputs!C11 -> 191.25 | I13: =G13+H13 -> 1616.25 | J13: =I13*Inputs!C20 -> 16.1625 | K13: =I13-J13 -> 1600.0875 | L13: =(F13/1000000)*Inputs!C12 -> 67.5 | M13: =Inputs!C13 -> 250 | N13: =Inputs!C14*Inputs!C15 -> 450 | O13: =Inputs!C16 -> 750 | P13: =Inputs!C17 -> 75 | Q13: =(K13*Inputs!C18) + ((C13+D13)*Inputs!C19) -> 76.877625 | R13: =L13+M13+N13+O13+P13+Q13 -> 1669.3776 | S13: =K13-R13 -> -69.290125
A14: 12 | B14: =B13*(1+Inputs!C7) -> 500 | C14: =B14*Inputs!C23 -> 75 | D14: =(B14-C14)*Inputs!C24 -> 21.25 | E14: =B14*Inputs!C8 -> 750 | F14: =E14*Inputs!C9 -> 22500000 | G14: =C14*Inputs!C10 -> 1425 | H14: =D14*Inputs!C11 -> 191.25 | I14: =G14+H14 -> 1616.25 | J14: =I14*Inputs!C20 -> 16.1625 | K14: =I14-J14 -> 1600.0875 | L14: =(F14/1000000)*Inputs!C12 -> 67.5 | M14: =Inputs!C13 -> 250 | N14: =Inputs!C14*Inputs!C15 -> 450 | O14: =Inputs!C16 -> 750 | P14: =Inputs!C17 -> 75 | Q14: =(K14*Inputs!C18) + ((C14+D14)*Inputs!C19) -> 76.877625 | R14: =L14+M14+N14+O14+P14+Q14 -> 1669.3776 | S14: =K14-R14 -> -69.290125

Sheet Unit Economics
A1: Unit Economics (Based on Month 1)
A2: Metric | B2: Value | C2: Notes
A3: MAU | B3: ='Monthly Forecast'!B3 -> 500 | C3: Monthly active users
A4: Subscribers | B4: ='Monthly Forecast'!C3 -> 75 | C4: Estimated subscribers in month
A5: One-time buyers | B5: ='Monthly Forecast'!D3 -> 21.25 | C5: Estimated one-time transactions
A6: Net Revenue | B6: ='Monthly Forecast'!K3 -> 1600.0875 | C6: After refunds
A7: Total Costs | B7: ='Monthly Forecast'!R3 -> 1669.3776 | C7: All modeled costs
A8: Operating Profit | B8: ='Monthly Forecast'!S3 -> -69.290125 | C8: Net revenue - total costs
A9: ARPU (Net Rev / MAU) | B9: ='Monthly Forecast'!K3/'Monthly Forecast'!B3 -> 3.200175 | C9: Per active user
A10: AI cost per active user | B10: ='Monthly Forecast'!L3/'Monthly Forecast'!B3 -> 0.135 | C10: Target <$0.20–$0.50
A11: Gross margin (Net Rev - AI - Fees) / Net Rev | B11: =(('Monthly Forecast'!K3-'Monthly Forecast'!L3-'Monthly Forecast'!Q3)/'Monthly Forecast'!K3) -> 0.90976892 | C11: High-level gross margin
A12: Subscription LTV (simple) | B12: =(Inputs!C10*(1-Inputs!C18) - ('Monthly Forecast'!L3/'Monthly Forecast'!C3)) / Inputs!C25 -> 146.08333 | C12: Contribution margin / churn (planning-grade)
A13: Paid customers (subs + one-time) | B13: ='Monthly Forecast'!C3+'Monthly Forecast'!D3 -> 96.25 | C13: Transactions count
A14: Blended CAC (Marketing / paid tx) | B14: =IF(('Monthly Forecast'!C3+'Monthly Forecast'!D3)=0,0, 'Monthly Forecast'!O3/('Monthly Forecast'!C3+'Monthly Forecast'!D3)) -> 7.7922078 | C14: Marketing spend / paid transactions
A15: Payback (months) = CAC / (LTV * churn) | B15: =IF(Inputs!C25=0,0, (IF(('Monthly Forecast'!C3+'Monthly Forecast'!D3)=0,0,'Monthly Forecast'!O3/('Monthly Forecast'!C3+'Monthly Forecast'!D3))) / ((Inputs!C10*(1-Inputs!C18) - ('Monthly Forecast'!L3/'Monthly Forecast'!C3))) ) -> 0.444507 | C15: Approx. months to recover CAC from sub contribution

Sheet Sensitivity
A1: Sensitivity: Profit vs Subscription Conversion & Marketing Spend (Month 1)
A3: Sub Conversion → | B3: 0.05 | C3: 0.1 | D3: 0.15 | E3: 0.2 | F3: 0.25 | G3: 0.3
A4: 0 | B4: =(((((Inputs!C6*B3)*Inputs!C10)+(((Inputs!C6-(Inputs!C6*B3))*Inputs!C24)*Inputs!C11))-((((Inputs!C6*B3)*Inputs!C10)+(((Inputs!C6-(Inputs!C6*B3))*Inputs!C24)*Inputs!C11))*Inputs!C20))-(((((Inputs!C6*Inputs!C8)*Inputs!C9)/1000000)*Inputs!C12)+Inputs!C13+(Inputs!C14*Inputs!C15)+0+Inputs!C17+((((((Inputs!C6*B3)*Inputs!C10)+(((Inputs!C6-(Inputs!C6*B3))*Inputs!C24)*Inputs!C11))-((((Inputs!C6*B3)*Inputs!C10)+(((Inputs!C6-(Inputs!C6*B3))*Inputs!C24)*Inputs!C11))*Inputs!C20))*Inputs!C18) + (((Inputs!C6*B3)+((Inputs!C6-(Inputs!C6*B3))*Inputs!C24))*Inputs!C19)))) -> -195.71838 | C4: =(((((Inputs!C6*C3)*Inputs!C10)+(((Inputs!C6-(Inputs!C6*C3))*Inputs!C24)*Inputs!C11))-((((Inputs!C6*C3)*Inputs!C10)+(((Inputs!C6-(Inputs!C6*C3))*Inputs!C24)*Inputs!C11))*Inputs!C20))-(((((Inputs!C6*Inputs!C8)*Inputs!C9)/1000000)*Inputs!C12)+Inputs!C13+(Inputs!C14*Inputs!C15)+0+Inputs!C17+((((((Inputs!C6*C3)*Inputs!C10)+(((Inputs!C6-(Inputs!C6*C3))*Inputs!C24)*Inputs!C11))-((((Inputs!C6*C3)*Inputs!C10)+(((Inputs!C6-(Inputs!C6*C3))*Inputs!C24)*Inputs!C11))*Inputs!C20))*Inputs!C18) + (((Inputs!C6*C3)+((Inputs!C6-(Inputs!C6*C3))*Inputs!C24))*Inputs!C19)))) -> 242.49575 | D4: =(((((Inputs!C6*D3)*Inputs!C10)+(((Inputs!C6-(Inputs!C6*D3))*Inputs!C24)*Inputs!C11))-((((Inputs!C6*D3)*Inputs!C10)+(((Inputs!C6-(Inputs!C6*D3))*Inputs!C24)*Inputs!C11))*Inputs!C20))-(((((Inputs!C6*Inputs!C8)*Inputs!C9)/1000000)*Inputs!C12)+Inputs!C13+(Inputs!C14*Inputs!C15)+0+Inputs!C17+((((((Inputs!C6*D3)*Inputs!C10)+(((Inputs!C6-(Inputs!C6*D3))*Inputs!C24)*Inputs!C11))-((((Inputs!C6*D3)*Inputs!C10)+(((Inputs!C6-(Inputs!C6*D3))*Inputs!C24)*Inputs!C11))*Inputs!C20))*Inputs!C18) + (((Inputs!C6*D3)+((Inputs!C6-(Inputs!C6*D3))*Inputs!C24))*Inputs!C19)))) -> 680.70988 | E4: =(((((Inputs!C6*E3)*Inputs!C10)+(((Inputs!C6-(Inputs!C6*E3))*Inputs!C24)*Inputs!C11))-((((Inputs!C6*E3)*Inputs!C10)+(((Inputs!C6-(Inputs!C6*E3))*Inputs!C24)*Inputs!C11))*Inputs!C20))-(((((Inputs!C6*Inputs!C8)*Inputs!C9)/1000000)*Inputs!C12)+Inputs!C13+(Inputs!C14*Inputs!C15)+0+Inputs!C17+((((((Inputs!C6*E3)*Inputs!C10)+(((Inputs!C6-(Inputs!C6*E3))*Inputs!C24)*Inputs!C11))-((((Inputs!C6*E3)*Inputs!C10)+(((Inputs!C6-(Inputs!C6*E3))*Inputs!C24)*Inputs!C11))*Inputs!C20))*Inputs!C18) + (((Inputs!C6*E3)+((Inputs!C6-(Inputs!C6*E3))*Inputs!C24))*Inputs!C19)))) -> 1118.924 | F4: =(((((Inputs!C6*F3)*Inputs!C10)+(((Inputs!C6-(Inputs!C6*F3))*Inputs!C24)*Inputs!C11))-((((Inputs!C6*F3)*Inputs!C10)+(((Inputs!C6-(Inputs!C6*F3))*Inputs!C24)*Inputs!C11))*Inputs!C20))-(((((Inputs!C6*Inputs!C8)*Inputs!C9)/1000000)*Inputs!C12)+Inputs!C13+(Inputs!C14*Inputs!C15)+0+Inputs!C17+((((((Inputs!C6*F3)*Inputs!C10)+(((Inputs!C6-(Inputs!C6*F3))*Inputs!C24)*Inputs!C11))-((((Inputs!C6*F3)*Inputs!C10)+(((Inputs!C6-(Inputs!C6*F3))*Inputs!C24)*Inputs!C11))*Inputs!C20))*Inputs!C18) + (((Inputs!C6*F3)+((Inputs!C6-(Inputs!C6*F3))*Inputs!C24))*Inputs!C19)))) -> 1557.1381 | G4: =(((((Inputs!C6*G3)*Inputs!C10)+(((Inputs!C6-(Inputs!C6*G3))*Inputs!C24)*Inputs!C11))-((((Inputs!C6*G3)*Inputs!C10)+(((Inputs!C6-(Inputs!C6*G3))*Inputs!C24)*Inputs!C11))*Inputs!C20))-(((((Inputs!C6*Inputs!C8)*Inputs!C9)/1000000)*Inputs!C12)+Inputs!C13+(Inputs!C14*Inputs!C15)+0+Inputs!C17+((((((Inputs!C6*G3)*Inputs!C10)+(((Inputs!C6-(Inputs!C6*G3))*Inputs!C24)*Inputs!C11))-((((Inputs!C6*G3)*Inputs!C10)+(((Inputs!C6-(Inputs!C6*G3))*Inputs!C24)*Inputs!C11))*Inputs!C20))*Inputs!C18) + (((Inputs!C6*G3)+((Inputs!C6-(Inputs!C6*G3))*Inputs!C24))*Inputs!C19)))) -> 1995.3523
A5: 250 | B5: =(((((Inputs!C6*B3)*Inputs!C10)+(((Inputs!C6-(Inputs!C6*B3))*Inputs!C24)*Inputs!C11))-((((Inputs!C6*B3)*Inputs!C10)+(((Inputs!C6-(Inputs!C6*B3))*Inputs!C24)*Inputs!C11))*Inputs!C20))-(((((Inputs!C6*Inputs!C8)*Inputs!C9)/1000000)*Inputs!C12)+Inputs!C13+(Inputs!C14*Inputs!C15)+250+Inputs!C17+((((((Inputs!C6*B3)*Inputs!C10)+(((Inputs!C6-(Inputs!C6*B3))*Inputs!C24)*Inputs!C11))-((((Inputs!C6*B3)*Inputs!C10)+(((Inputs!C6-(Inputs!C6*B3))*Inputs!C24)*Inputs!C11))*Inputs!C20))*Inputs!C18) + (((Inputs!C6*B3)+((Inputs!C6-(Inputs!C6*B3))*Inputs!C24))*Inputs!C19)))) -> -445.71838 | C5: =(((((Inputs!C6*C3)*Inputs!C10)+(((Inputs!C6-(Inputs!C6*C3))*Inputs!C24)*Inputs!C11))-((((Inputs!C6*C3)*Inputs!C10)+(((Inputs!C6-(Inputs!C6*C3))*Inputs!C24)*Inputs!C11))*Inputs!C20))-(((((Inputs!C6*Inputs!C8)*Inputs!C9)/1000000)*Inputs!C12)+Inputs!C13+(Inputs!C14*Inputs!C15)+250+Inputs!C17+((((((Inputs!C6*C3)*Inputs!C10)+(((Inputs!C6-(Inputs!C6*C3))*Inputs!C24)*Inputs!C11))-((((Inputs!C6*C3)*Inputs!C10)+(((Inputs!C6-(Inputs!C6*C3))*Inputs!C24)*Inputs!C11))*Inputs!C20))*Inputs!C18) + (((Inputs!C6*C3)+((Inputs!C6-(Inputs!C6*C3))*Inputs!C24))*Inputs!C19)))) -> -7.50425 | D5: =(((((Inputs!C6*D3)*Inputs!C10)+(((Inputs!C6-(Inputs!C6*D3))*Inputs!C24)*Inputs!C11))-((((Inputs!C6*D3)*Inputs!C10)+(((Inputs!C6-(Inputs!C6*D3))*Inputs!C24)*Inputs!C11))*Inputs!C20))-(((((Inputs!C6*Inputs!C8)*Inputs!C9)/1000000)*Inputs!C12)+Inputs!C13+(Inputs!C14*Inputs!C15)+250+Inputs!C17+((((((Inputs!C6*D3)*Inputs!C10)+(((Inputs!C6-(Inputs!C6*D3))*Inputs!C24)*Inputs!C11))-((((Inputs!C6*D3)*Inputs!C10)+(((Inputs!C6-(Inputs!C6*D3))*Inputs!C24)*Inputs!C11))*Inputs!C20))*Inputs!C18) + (((Inputs!C6*D3)+((Inputs!C6-(Inputs!C6*D3))*Inputs!C24))*Inputs!C19)))) -> 430.70988 | E5: =(((((Inputs!C6*E3)*Inputs!C10)+(((Inputs!C6-(Inputs!C6*E3))*Inputs!C24)*Inputs!C11))-((((Inputs!C6*E3)*Inputs!C10)+(((Inputs!C6-(Inputs!C6*E3))*Inputs!C24)*Inputs!C11))*Inputs!C20))-(((((Inputs!C6*Inputs!C8)*Inputs!C9)/1000000)*Inputs!C12)+Inputs!C13+(Inputs!C14*Inputs!C15)+250+Inputs!C17+((((((Inputs!C6*E3)*Inputs!C10)+(((Inputs!C6-(Inputs!C6*E3))*Inputs!C24)*Inputs!C11))-((((Inputs!C6*E3)*Inputs!C10)+(((Inputs!C6-(Inputs!C6*E3))*Inputs!C24)*Inputs!C11))*Inputs!C20))*Inputs!C18) + (((Inputs!C6*E3)+((Inputs!C6-(Inputs!C6*E3))*Inputs!C24))*Inputs!C19)))) -> 868.924 | F5: =(((((Inputs!C6*F3)*Inputs!C10)+(((Inputs!C6-(Inputs!C6*F3))*Inputs!C24)*Inputs!C11))-((((Inputs!C6*F3)*Inputs!C10)+(((Inputs!C6-(Inputs!C6*F3))*Inputs!C24)*Inputs!C11))*Inputs!C20))-(((((Inputs!C6*Inputs!C8)*Inputs!C9)/1000000)*Inputs!C12)+Inputs!C13+(Inputs!C14*Inputs!C15)+250+Inputs!C17+((((((Inputs!C6*F3)*Inputs!C10)+(((Inputs!C6-(Inputs!C6*F3))*Inputs!C24)*Inputs!C11))-((((Inputs!C6*F3)*Inputs!C10)+(((Inputs!C6-(Inputs!C6*F3))*Inputs!C24)*Inputs!C11))*Inputs!C20))*Inputs!C18) + (((Inputs!C6*F3)+((Inputs!C6-(Inputs!C6*F3))*Inputs!C24))*Inputs!C19)))) -> 1307.1381 | G5: =(((((Inputs!C6*G3)*Inputs!C10)+(((Inputs!C6-(Inputs!C6*G3))*Inputs!C24)*Inputs!C11))-((((Inputs!C6*G3)*Inputs!C10)+(((Inputs!C6-(Inputs!C6*G3))*Inputs!C24)*Inputs!C11))*Inputs!C20))-(((((Inputs!C6*Inputs!C8)*Inputs!C9)/1000000)*Inputs!C12)+Inputs!C13+(Inputs!C14*Inputs!C15)+250+Inputs!C17+((((((Inputs!C6*G3)*Inputs!C10)+(((Inputs!C6-(Inputs!C6*G3))*Inputs!C24)*Inputs!C11))-((((Inputs!C6*G3)*Inputs!C10)+(((Inputs!C6-(Inputs!C6*G3))*Inputs!C24)*Inputs!C11))*Inputs!C20))*Inputs!C18) + (((Inputs!C6*G3)+((Inputs!C6-(Inputs!C6*G3))*Inputs!C24))*Inputs!C19)))) -> 1745.3523
A6: 500 | B6: =(((((Inputs!C6*B3)*Inputs!C10)+(((Inputs!C6-(Inputs!C6*B3))*Inputs!C24)*Inputs!C11))-((((Inputs!C6*B3)*Inputs!C10)+(((Inputs!C6-(Inputs!C6*B3))*Inputs!C24)*Inputs!C11))*Inputs!C20))-(((((Inputs!C6*Inputs!C8)*Inputs!C9)/1000000)*Inputs!C12)+Inputs!C13+(Inputs!C14*Inputs!C15)+500+Inputs!C17+((((((Inputs!C6*B3)*Inputs!C10)+(((Inputs!C6-(Inputs!C6*B3))*Inputs!C24)*Inputs!C11))-((((Inputs!C6*B3)*Inputs!C10)+(((Inputs!C6-(Inputs!C6*B3))*Inputs!C24)*Inputs!C11))*Inputs!C20))*Inputs!C18) + (((Inputs!C6*B3)+((Inputs!C6-(Inputs!C6*B3))*Inputs!C24))*Inputs!C19)))) -> -695.71838 | C6: =(((((Inputs!C6*C3)*Inputs!C10)+(((Inputs!C6-(Inputs!C6*C3))*Inputs!C24)*Inputs!C11))-((((Inputs!C6*C3)*Inputs!C10)+(((Inputs!C6-(Inputs!C6*C3))*Inputs!C24)*Inputs!C11))*Inputs!C20))-(((((Inputs!C6*Inputs!C8)*Inputs!C9)/1000000)*Inputs!C12)+Inputs!C13+(Inputs!C14*Inputs!C15)+500+Inputs!C17+((((((Inputs!C6*C3)*Inputs!C10)+(((Inputs!C6-(Inputs!C6*C3))*Inputs!C24)*Inputs!C11))-((((Inputs!C6*C3)*Inputs!C10)+(((Inputs!C6-(Inputs!C6*C3))*Inputs!C24)*Inputs!C11))*Inputs!C20))*Inputs!C18) + (((Inputs!C6*C3)+((Inputs!C6-(Inputs!C6*C3))*Inputs!C24))*Inputs!C19)))) -> -257.50425 | D6: =(((((Inputs!C6*D3)*Inputs!C10)+(((Inputs!C6-(Inputs!C6*D3))*Inputs!C24)*Inputs!C11))-((((Inputs!C6*D3)*Inputs!C10)+(((Inputs!C6-(Inputs!C6*D3))*Inputs!C24)*Inputs!C11))*Inputs!C20))-(((((Inputs!C6*Inputs!C8)*Inputs!C9)/1000000)*Inputs!C12)+Inputs!C13+(Inputs!C14*Inputs!C15)+500+Inputs!C17+((((((Inputs!C6*D3)*Inputs!C10)+(((Inputs!C6-(Inputs!C6*D3))*Inputs!C24)*Inputs!C11))-((((Inputs!C6*D3)*Inputs!C10)+(((Inputs!C6-(Inputs!C6*D3))*Inputs!C24)*Inputs!C11))*Inputs!C20))*Inputs!C18) + (((Inputs!C6*D3)+((Inputs!C6-(Inputs!C6*D3))*Inputs!C24))*Inputs!C19)))) -> 180.70988 | E6: =(((((Inputs!C6*E3)*Inputs!C10)+(((Inputs!C6-(Inputs!C6*E3))*Inputs!C24)*Inputs!C11))-((((Inputs!C6*E3)*Inputs!C10)+(((Inputs!C6-(Inputs!C6*E3))*Inputs!C24)*Inputs!C11))*Inputs!C20))-(((((Inputs!C6*Inputs!C8)*Inputs!C9)/1000000)*Inputs!C12)+Inputs!C13+(Inputs!C14*Inputs!C15)+500+Inputs!C17+((((((Inputs!C6*E3)*Inputs!C10)+(((Inputs!C6-(Inputs!C6*E3))*Inputs!C24)*Inputs!C11))-((((Inputs!C6*E3)*Inputs!C10)+(((Inputs!C6-(Inputs!C6*E3))*Inputs!C24)*Inputs!C11))*Inputs!C20))*Inputs!C18) + (((Inputs!C6*E3)+((Inputs!C6-(Inputs!C6*E3))*Inputs!C24))*Inputs!C19)))) -> 618.924 | F6: =(((((Inputs!C6*F3)*Inputs!C10)+(((Inputs!C6-(Inputs!C6*F3))*Inputs!C24)*Inputs!C11))-((((Inputs!C6*F3)*Inputs!C10)+(((Inputs!C6-(Inputs!C6*F3))*Inputs!C24)*Inputs!C11))*Inputs!C20))-(((((Inputs!C6*Inputs!C8)*Inputs!C9)/1000000)*Inputs!C12)+Inputs!C13+(Inputs!C14*Inputs!C15)+500+Inputs!C17+((((((Inputs!C6*F3)*Inputs!C10)+(((Inputs!C6-(Inputs!C6*F3))*Inputs!C24)*Inputs!C11))-((((Inputs!C6*F3)*Inputs!C10)+(((Inputs!C6-(Inputs!C6*F3))*Inputs!C24)*Inputs!C11))*Inputs!C20))*Inputs!C18) + (((Inputs!C6*F3)+((Inputs!C6-(Inputs!C6*F3))*Inputs!C24))*Inputs!C19)))) -> 1057.1381 | G6: =(((((Inputs!C6*G3)*Inputs!C10)+(((Inputs!C6-(Inputs!C6*G3))*Inputs!C24)*Inputs!C11))-((((Inputs!C6*G3)*Inputs!C10)+(((Inputs!C6-(Inputs!C6*G3))*Inputs!C24)*Inputs!C11))*Inputs!C20))-(((((Inputs!C6*Inputs!C8)*Inputs!C9)/1000000)*Inputs!C12)+Inputs!C13+(Inputs!C14*Inputs!C15)+500+Inputs!C17+((((((Inputs!C6*G3)*Inputs!C10)+(((Inputs!C6-(Inputs!C6*G3))*Inputs!C24)*Inputs!C11))-((((Inputs!C6*G3)*Inputs!C10)+(((Inputs!C6-(Inputs!C6*G3))*Inputs!C24)*Inputs!C11))*Inputs!C20))*Inputs!C18) + (((Inputs!C6*G3)+((Inputs!C6-(Inputs!C6*G3))*Inputs!C24))*Inputs!C19)))) -> 1495.3523
A7: 750 | B7: =(((((Inputs!C6*B3)*Inputs!C10)+(((Inputs!C6-(Inputs!C6*B3))*Inputs!C24)*Inputs!C11))-((((Inputs!C6*B3)*Inputs!C10)+(((Inputs!C6-(Inputs!C6*B3))*Inputs!C24)*Inputs!C11))*Inputs!C20))-(((((Inputs!C6*Inputs!C8)*Inputs!C9)/1000000)*Inputs!C12)+Inputs!C13+(Inputs!C14*Inputs!C15)+750+Inputs!C17+((((((Inputs!C6*B3)*Inputs!C10)+(((Inputs!C6-(Inputs!C6*B3))*Inputs!C24)*Inputs!C11))-((((Inputs!C6*B3)*Inputs!C10)+(((Inputs!C6-(Inputs!C6*B3))*Inputs!C24)*Inputs!C11))*Inputs!C20))*Inputs!C18) + (((Inputs!C6*B3)+((Inputs!C6-(Inputs!C6*B3))*Inputs!C24))*Inputs!C19)))) -> -945.71838 | C7: =(((((Inputs!C6*C3)*Inputs!C10)+(((Inputs!C6-(Inputs!C6*C3))*Inputs!C24)*Inputs!C11))-((((Inputs!C6*C3)*Inputs!C10)+(((Inputs!C6-(Inputs!C6*C3))*Inputs!C24)*Inputs!C11))*Inputs!C20))-(((((Inputs!C6*Inputs!C8)*Inputs!C9)/1000000)*Inputs!C12)+Inputs!C13+(Inputs!C14*Inputs!C15)+750+Inputs!C17+((((((Inputs!C6*C3)*Inputs!C10)+(((Inputs!C6-(Inputs!C6*C3))*Inputs!C24)*Inputs!C11))-((((Inputs!C6*C3)*Inputs!C10)+(((Inputs!C6-(Inputs!C6*C3))*Inputs!C24)*Inputs!C11))*Inputs!C20))*Inputs!C18) + (((Inputs!C6*C3)+((Inputs!C6-(Inputs!C6*C3))*Inputs!C24))*Inputs!C19)))) -> -507.50425 | D7: =(((((Inputs!C6*D3)*Inputs!C10)+(((Inputs!C6-(Inputs!C6*D3))*Inputs!C24)*Inputs!C11))-((((Inputs!C6*D3)*Inputs!C10)+(((Inputs!C6-(Inputs!C6*D3))*Inputs!C24)*Inputs!C11))*Inputs!C20))-(((((Inputs!C6*Inputs!C8)*Inputs!C9)/1000000)*Inputs!C12)+Inputs!C13+(Inputs!C14*Inputs!C15)+750+Inputs!C17+((((((Inputs!C6*D3)*Inputs!C10)+(((Inputs!C6-(Inputs!C6*D3))*Inputs!C24)*Inputs!C11))-((((Inputs!C6*D3)*Inputs!C10)+(((Inputs!C6-(Inputs!C6*D3))*Inputs!C24)*Inputs!C11))*Inputs!C20))*Inputs!C18) + (((Inputs!C6*D3)+((Inputs!C6-(Inputs!C6*D3))*Inputs!C24))*Inputs!C19)))) -> -69.290125 | E7: =(((((Inputs!C6*E3)*Inputs!C10)+(((Inputs!C6-(Inputs!C6*E3))*Inputs!C24)*Inputs!C11))-((((Inputs!C6*E3)*Inputs!C10)+(((Inputs!C6-(Inputs!C6*E3))*Inputs!C24)*Inputs!C11))*Inputs!C20))-(((((Inputs!C6*Inputs!C8)*Inputs!C9)/1000000)*Inputs!C12)+Inputs!C13+(Inputs!C14*Inputs!C15)+750+Inputs!C17+((((((Inputs!C6*E3)*Inputs!C10)+(((Inputs!C6-(Inputs!C6*E3))*Inputs!C24)*Inputs!C11))-((((Inputs!C6*E3)*Inputs!C10)+(((Inputs!C6-(Inputs!C6*E3))*Inputs!C24)*Inputs!C11))*Inputs!C20))*Inputs!C18) + (((Inputs!C6*E3)+((Inputs!C6-(Inputs!C6*E3))*Inputs!C24))*Inputs!C19)))) -> 368.924 | F7: =(((((Inputs!C6*F3)*Inputs!C10)+(((Inputs!C6-(Inputs!C6*F3))*Inputs!C24)*Inputs!C11))-((((Inputs!C6*F3)*Inputs!C10)+(((Inputs!C6-(Inputs!C6*F3))*Inputs!C24)*Inputs!C11))*Inputs!C20))-(((((Inputs!C6*Inputs!C8)*Inputs!C9)/1000000)*Inputs!C12)+Inputs!C13+(Inputs!C14*Inputs!C15)+750+Inputs!C17+((((((Inputs!C6*F3)*Inputs!C10)+(((Inputs!C6-(Inputs!C6*F3))*Inputs!C24)*Inputs!C11))-((((Inputs!C6*F3)*Inputs!C10)+(((Inputs!C6-(Inputs!C6*F3))*Inputs!C24)*Inputs!C11))*Inputs!C20))*Inputs!C18) + (((Inputs!C6*F3)+((Inputs!C6-(Inputs!C6*F3))*Inputs!C24))*Inputs!C19)))) -> 807.13812 | G7: =(((((Inputs!C6*G3)*Inputs!C10)+(((Inputs!C6-(Inputs!C6*G3))*Inputs!C24)*Inputs!C11))-((((Inputs!C6*G3)*Inputs!C10)+(((Inputs!C6-(Inputs!C6*G3))*Inputs!C24)*Inputs!C11))*Inputs!C20))-(((((Inputs!C6*Inputs!C8)*Inputs!C9)/1000000)*Inputs!C12)+Inputs!C13+(Inputs!C14*Inputs!C15)+750+Inputs!C17+((((((Inputs!C6*G3)*Inputs!C10)+(((Inputs!C6-(Inputs!C6*G3))*Inputs!C24)*Inputs!C11))-((((Inputs!C6*G3)*Inputs!C10)+(((Inputs!C6-(Inputs!C6*G3))*Inputs!C24)*Inputs!C11))*Inputs!C20))*Inputs!C18) + (((Inputs!C6*G3)+((Inputs!C6-(Inputs!C6*G3))*Inputs!C24))*Inputs!C19)))) -> 1245.3523
A8: 1000 | B8: =(((((Inputs!C6*B3)*Inputs!C10)+(((Inputs!C6-(Inputs!C6*B3))*Inputs!C24)*Inputs!C11))-((((Inputs!C6*B3)*Inputs!C10)+(((Inputs!C6-(Inputs!C6*B3))*Inputs!C24)*Inputs!C11))*Inputs!C20))-(((((Inputs!C6*Inputs!C8)*Inputs!C9)/1000000)*Inputs!C12)+Inputs!C13+(Inputs!C14*Inputs!C15)+1000+Inputs!C17+((((((Inputs!C6*B3)*Inputs!C10)+(((Inputs!C6-(Inputs!C6*B3))*Inputs!C24)*Inputs!C11))-((((Inputs!C6*B3)*Inputs!C10)+(((Inputs!C6-(Inputs!C6*B3))*Inputs!C24)*Inputs!C11))*Inputs!C20))*Inputs!C18) + (((Inputs!C6*B3)+((Inputs!C6-(Inputs!C6*B3))*Inputs!C24))*Inputs!C19)))) -> -1195.7184 | C8: =(((((Inputs!C6*C3)*Inputs!C10)+(((Inputs!C6-(Inputs!C6*C3))*Inputs!C24)*Inputs!C11))-((((Inputs!C6*C3)*Inputs!C10)+(((Inputs!C6-(Inputs!C6*C3))*Inputs!C24)*Inputs!C11))*Inputs!C20))-(((((Inputs!C6*Inputs!C8)*Inputs!C9)/1000000)*Inputs!C12)+Inputs!C13+(Inputs!C14*Inputs!C15)+1000+Inputs!C17+((((((Inputs!C6*C3)*Inputs!C10)+(((Inputs!C6-(Inputs!C6*C3))*Inputs!C24)*Inputs!C11))-((((Inputs!C6*C3)*Inputs!C10)+(((Inputs!C6-(Inputs!C6*C3))*Inputs!C24)*Inputs!C11))*Inputs!C20))*Inputs!C18) + (((Inputs!C6*C3)+((Inputs!C6-(Inputs!C6*C3))*Inputs!C24))*Inputs!C19)))) -> -757.50425 | D8: =(((((Inputs!C6*D3)*Inputs!C10)+(((Inputs!C6-(Inputs!C6*D3))*Inputs!C24)*Inputs!C11))-((((Inputs!C6*D3)*Inputs!C10)+(((Inputs!C6-(Inputs!C6*D3))*Inputs!C24)*Inputs!C11))*Inputs!C20))-(((((Inputs!C6*Inputs!C8)*Inputs!C9)/1000000)*Inputs!C12)+Inputs!C13+(Inputs!C14*Inputs!C15)+1000+Inputs!C17+((((((Inputs!C6*D3)*Inputs!C10)+(((Inputs!C6-(Inputs!C6*D3))*Inputs!C24)*Inputs!C11))-((((Inputs!C6*D3)*Inputs!C10)+(((Inputs!C6-(Inputs!C6*D3))*Inputs!C24)*Inputs!C11))*Inputs!C20))*Inputs!C18) + (((Inputs!C6*D3)+((Inputs!C6-(Inputs!C6*D3))*Inputs!C24))*Inputs!C19)))) -> -319.29012 | E8: =(((((Inputs!C6*E3)*Inputs!C10)+(((Inputs!C6-(Inputs!C6*E3))*Inputs!C24)*Inputs!C11))-((((Inputs!C6*E3)*Inputs!C10)+(((Inputs!C6-(Inputs!C6*E3))*Inputs!C24)*Inputs!C11))*Inputs!C20))-(((((Inputs!C6*Inputs!C8)*Inputs!C9)/1000000)*Inputs!C12)+Inputs!C13+(Inputs!C14*Inputs!C15)+1000+Inputs!C17+((((((Inputs!C6*E3)*Inputs!C10)+(((Inputs!C6-(Inputs!C6*E3))*Inputs!C24)*Inputs!C11))-((((Inputs!C6*E3)*Inputs!C10)+(((Inputs!C6-(Inputs!C6*E3))*Inputs!C24)*Inputs!C11))*Inputs!C20))*Inputs!C18) + (((Inputs!C6*E3)+((Inputs!C6-(Inputs!C6*E3))*Inputs!C24))*Inputs!C19)))) -> 118.924 | F8: =(((((Inputs!C6*F3)*Inputs!C10)+(((Inputs!C6-(Inputs!C6*F3))*Inputs!C24)*Inputs!C11))-((((Inputs!C6*F3)*Inputs!C10)+(((Inputs!C6-(Inputs!C6*F3))*Inputs!C24)*Inputs!C11))*Inputs!C20))-(((((Inputs!C6*Inputs!C8)*Inputs!C9)/1000000)*Inputs!C12)+Inputs!C13+(Inputs!C14*Inputs!C15)+1000+Inputs!C17+((((((Inputs!C6*F3)*Inputs!C10)+(((Inputs!C6-(Inputs!C6*F3))*Inputs!C24)*Inputs!C11))-((((Inputs!C6*F3)*Inputs!C10)+(((Inputs!C6-(Inputs!C6*F3))*Inputs!C24)*Inputs!C11))*Inputs!C20))*Inputs!C18) + (((Inputs!C6*F3)+((Inputs!C6-(Inputs!C6*F3))*Inputs!C24))*Inputs!C19)))) -> 557.13812 | G8: =(((((Inputs!C6*G3)*Inputs!C10)+(((Inputs!C6-(Inputs!C6*G3))*Inputs!C24)*Inputs!C11))-((((Inputs!C6*G3)*Inputs!C10)+(((Inputs!C6-(Inputs!C6*G3))*Inputs!C24)*Inputs!C11))*Inputs!C20))-(((((Inputs!C6*Inputs!C8)*Inputs!C9)/1000000)*Inputs!C12)+Inputs!C13+(Inputs!C14*Inputs!C15)+1000+Inputs!C17+((((((Inputs!C6*G3)*Inputs!C10)+(((Inputs!C6-(Inputs!C6*G3))*Inputs!C24)*Inputs!C11))-((((Inputs!C6*G3)*Inputs!C10)+(((Inputs!C6-(Inputs!C6*G3))*Inputs!C24)*Inputs!C11))*Inputs!C20))*Inputs!C18) + (((Inputs!C6*G3)+((Inputs!C6-(Inputs!C6*G3))*Inputs!C24))*Inputs!C19)))) -> 995.35225
A9: 1250 | B9: =(((((Inputs!C6*B3)*Inputs!C10)+(((Inputs!C6-(Inputs!C6*B3))*Inputs!C24)*Inputs!C11))-((((Inputs!C6*B3)*Inputs!C10)+(((Inputs!C6-(Inputs!C6*B3))*Inputs!C24)*Inputs!C11))*Inputs!C20))-(((((Inputs!C6*Inputs!C8)*Inputs!C9)/1000000)*Inputs!C12)+Inputs!C13+(Inputs!C14*Inputs!C15)+1250+Inputs!C17+((((((Inputs!C6*B3)*Inputs!C10)+(((Inputs!C6-(Inputs!C6*B3))*Inputs!C24)*Inputs!C11))-((((Inputs!C6*B3)*Inputs!C10)+(((Inputs!C6-(Inputs!C6*B3))*Inputs!C24)*Inputs!C11))*Inputs!C20))*Inputs!C18) + (((Inputs!C6*B3)+((Inputs!C6-(Inputs!C6*B3))*Inputs!C24))*Inputs!C19)))) -> -1445.7184 | C9: =(((((Inputs!C6*C3)*Inputs!C10)+(((Inputs!C6-(Inputs!C6*C3))*Inputs!C24)*Inputs!C11))-((((Inputs!C6*C3)*Inputs!C10)+(((Inputs!C6-(Inputs!C6*C3))*Inputs!C24)*Inputs!C11))*Inputs!C20))-(((((Inputs!C6*Inputs!C8)*Inputs!C9)/1000000)*Inputs!C12)+Inputs!C13+(Inputs!C14*Inputs!C15)+1250+Inputs!C17+((((((Inputs!C6*C3)*Inputs!C10)+(((Inputs!C6-(Inputs!C6*C3))*Inputs!C24)*Inputs!C11))-((((Inputs!C6*C3)*Inputs!C10)+(((Inputs!C6-(Inputs!C6*C3))*Inputs!C24)*Inputs!C11))*Inputs!C20))*Inputs!C18) + (((Inputs!C6*C3)+((Inputs!C6-(Inputs!C6*C3))*Inputs!C24))*Inputs!C19)))) -> -1007.5042 | D9: =(((((Inputs!C6*D3)*Inputs!C10)+(((Inputs!C6-(Inputs!C6*D3))*Inputs!C24)*Inputs!C11))-((((Inputs!C6*D3)*Inputs!C10)+(((Inputs!C6-(Inputs!C6*D3))*Inputs!C24)*Inputs!C11))*Inputs!C20))-(((((Inputs!C6*Inputs!C8)*Inputs!C9)/1000000)*Inputs!C12)+Inputs!C13+(Inputs!C14*Inputs!C15)+1250+Inputs!C17+((((((Inputs!C6*D3)*Inputs!C10)+(((Inputs!C6-(Inputs!C6*D3))*Inputs!C24)*Inputs!C11))-((((Inputs!C6*D3)*Inputs!C10)+(((Inputs!C6-(Inputs!C6*D3))*Inputs!C24)*Inputs!C11))*Inputs!C20))*Inputs!C18) + (((Inputs!C6*D3)+((Inputs!C6-(Inputs!C6*D3))*Inputs!C24))*Inputs!C19)))) -> -569.29012 | E9: =(((((Inputs!C6*E3)*Inputs!C10)+(((Inputs!C6-(Inputs!C6*E3))*Inputs!C24)*Inputs!C11))-((((Inputs!C6*E3)*Inputs!C10)+(((Inputs!C6-(Inputs!C6*E3))*Inputs!C24)*Inputs!C11))*Inputs!C20))-(((((Inputs!C6*Inputs!C8)*Inputs!C9)/1000000)*Inputs!C12)+Inputs!C13+(Inputs!C14*Inputs!C15)+1250+Inputs!C17+((((((Inputs!C6*E3)*Inputs!C10)+(((Inputs!C6-(Inputs!C6*E3))*Inputs!C24)*Inputs!C11))-((((Inputs!C6*E3)*Inputs!C10)+(((Inputs!C6-(Inputs!C6*E3))*Inputs!C24)*Inputs!C11))*Inputs!C20))*Inputs!C18) + (((Inputs!C6*E3)+((Inputs!C6-(Inputs!C6*E3))*Inputs!C24))*Inputs!C19)))) -> -131.076 | F9: =(((((Inputs!C6*F3)*Inputs!C10)+(((Inputs!C6-(Inputs!C6*F3))*Inputs!C24)*Inputs!C11))-((((Inputs!C6*F3)*Inputs!C10)+(((Inputs!C6-(Inputs!C6*F3))*Inputs!C24)*Inputs!C11))*Inputs!C20))-(((((Inputs!C6*Inputs!C8)*Inputs!C9)/1000000)*Inputs!C12)+Inputs!C13+(Inputs!C14*Inputs!C15)+1250+Inputs!C17+((((((Inputs!C6*F3)*Inputs!C10)+(((Inputs!C6-(Inputs!C6*F3))*Inputs!C24)*Inputs!C11))-((((Inputs!C6*F3)*Inputs!C10)+(((Inputs!C6-(Inputs!C6*F3))*Inputs!C24)*Inputs!C11))*Inputs!C20))*Inputs!C18) + (((Inputs!C6*F3)+((Inputs!C6-(Inputs!C6*F3))*Inputs!C24))*Inputs!C19)))) -> 307.13812 | G9: =(((((Inputs!C6*G3)*Inputs!C10)+(((Inputs!C6-(Inputs!C6*G3))*Inputs!C24)*Inputs!C11))-((((Inputs!C6*G3)*Inputs!C10)+(((Inputs!C6-(Inputs!C6*G3))*Inputs!C24)*Inputs!C11))*Inputs!C20))-(((((Inputs!C6*Inputs!C8)*Inputs!C9)/1000000)*Inputs!C12)+Inputs!C13+(Inputs!C14*Inputs!C15)+1250+Inputs!C17+((((((Inputs!C6*G3)*Inputs!C10)+(((Inputs!C6-(Inputs!C6*G3))*Inputs!C24)*Inputs!C11))-((((Inputs!C6*G3)*Inputs!C10)+(((Inputs!C6-(Inputs!C6*G3))*Inputs!C24)*Inputs!C11))*Inputs!C20))*Inputs!C18) + (((Inputs!C6*G3)+((Inputs!C6-(Inputs!C6*G3))*Inputs!C24))*Inputs!C19)))) -> 745.35225
A10: 1500 | B10: =(((((Inputs!C6*B3)*Inputs!C10)+(((Inputs!C6-(Inputs!C6*B3))*Inputs!C24)*Inputs!C11))-((((Inputs!C6*B3)*Inputs!C10)+(((Inputs!C6-(Inputs!C6*B3))*Inputs!C24)*Inputs!C11))*Inputs!C20))-(((((Inputs!C6*Inputs!C8)*Inputs!C9)/1000000)*Inputs!C12)+Inputs!C13+(Inputs!C14*Inputs!C15)+1500+Inputs!C17+((((((Inputs!C6*B3)*Inputs!C10)+(((Inputs!C6-(Inputs!C6*B3))*Inputs!C24)*Inputs!C11))-((((Inputs!C6*B3)*Inputs!C10)+(((Inputs!C6-(Inputs!C6*B3))*Inputs!C24)*Inputs!C11))*Inputs!C20))*Inputs!C18) + (((Inputs!C6*B3)+((Inputs!C6-(Inputs!C6*B3))*Inputs!C24))*Inputs!C19)))) -> -1695.7184 | C10: =(((((Inputs!C6*C3)*Inputs!C10)+(((Inputs!C6-(Inputs!C6*C3))*Inputs!C24)*Inputs!C11))-((((Inputs!C6*C3)*Inputs!C10)+(((Inputs!C6-(Inputs!C6*C3))*Inputs!C24)*Inputs!C11))*Inputs!C20))-(((((Inputs!C6*Inputs!C8)*Inputs!C9)/1000000)*Inputs!C12)+Inputs!C13+(Inputs!C14*Inputs!C15)+1500+Inputs!C17+((((((Inputs!C6*C3)*Inputs!C10)+(((Inputs!C6-(Inputs!C6*C3))*Inputs!C24)*Inputs!C11))-((((Inputs!C6*C3)*Inputs!C10)+(((Inputs!C6-(Inputs!C6*C3))*Inputs!C24)*Inputs!C11))*Inputs!C20))*Inputs!C18) + (((Inputs!C6*C3)+((Inputs!C6-(Inputs!C6*C3))*Inputs!C24))*Inputs!C19)))) -> -1257.5042 | D10: =(((((Inputs!C6*D3)*Inputs!C10)+(((Inputs!C6-(Inputs!C6*D3))*Inputs!C24)*Inputs!C11))-((((Inputs!C6*D3)*Inputs!C10)+(((Inputs!C6-(Inputs!C6*D3))*Inputs!C24)*Inputs!C11))*Inputs!C20))-(((((Inputs!C6*Inputs!C8)*Inputs!C9)/1000000)*Inputs!C12)+Inputs!C13+(Inputs!C14*Inputs!C15)+1500+Inputs!C17+((((((Inputs!C6*D3)*Inputs!C10)+(((Inputs!C6-(Inputs!C6*D3))*Inputs!C24)*Inputs!C11))-((((Inputs!C6*D3)*Inputs!C10)+(((Inputs!C6-(Inputs!C6*D3))*Inputs!C24)*Inputs!C11))*Inputs!C20))*Inputs!C18) + (((Inputs!C6*D3)+((Inputs!C6-(Inputs!C6*D3))*Inputs!C24))*Inputs!C19)))) -> -819.29012 | E10: =(((((Inputs!C6*E3)*Inputs!C10)+(((Inputs!C6-(Inputs!C6*E3))*Inputs!C24)*Inputs!C11))-((((Inputs!C6*E3)*Inputs!C10)+(((Inputs!C6-(Inputs!C6*E3))*Inputs!C24)*Inputs!C11))*Inputs!C20))-(((((Inputs!C6*Inputs!C8)*Inputs!C9)/1000000)*Inputs!C12)+Inputs!C13+(Inputs!C14*Inputs!C15)+1500+Inputs!C17+((((((Inputs!C6*E3)*Inputs!C10)+(((Inputs!C6-(Inputs!C6*E3))*Inputs!C24)*Inputs!C11))-((((Inputs!C6*E3)*Inputs!C10)+(((Inputs!C6-(Inputs!C6*E3))*Inputs!C24)*Inputs!C11))*Inputs!C20))*Inputs!C18) + (((Inputs!C6*E3)+((Inputs!C6-(Inputs!C6*E3))*Inputs!C24))*Inputs!C19)))) -> -381.076 | F10: =(((((Inputs!C6*F3)*Inputs!C10)+(((Inputs!C6-(Inputs!C6*F3))*Inputs!C24)*Inputs!C11))-((((Inputs!C6*F3)*Inputs!C10)+(((Inputs!C6-(Inputs!C6*F3))*Inputs!C24)*Inputs!C11))*Inputs!C20))-(((((Inputs!C6*Inputs!C8)*Inputs!C9)/1000000)*Inputs!C12)+Inputs!C13+(Inputs!C14*Inputs!C15)+1500+Inputs!C17+((((((Inputs!C6*F3)*Inputs!C10)+(((Inputs!C6-(Inputs!C6*F3))*Inputs!C24)*Inputs!C11))-((((Inputs!C6*F3)*Inputs!C10)+(((Inputs!C6-(Inputs!C6*F3))*Inputs!C24)*Inputs!C11))*Inputs!C20))*Inputs!C18) + (((Inputs!C6*F3)+((Inputs!C6-(Inputs!C6*F3))*Inputs!C24))*Inputs!C19)))) -> 57.138125 | G10: =(((((Inputs!C6*G3)*Inputs!C10)+(((Inputs!C6-(Inputs!C6*G3))*Inputs!C24)*Inputs!C11))-((((Inputs!C6*G3)*Inputs!C10)+(((Inputs!C6-(Inputs!C6*G3))*Inputs!C24)*Inputs!C11))*Inputs!C20))-(((((Inputs!C6*Inputs!C8)*Inputs!C9)/1000000)*Inputs!C12)+Inputs!C13+(Inputs!C14*Inputs!C15)+1500+Inputs!C17+((((((Inputs!C6*G3)*Inputs!C10)+(((Inputs!C6-(Inputs!C6*G3))*Inputs!C24)*Inputs!C11))-((((Inputs!C6*G3)*Inputs!C10)+(((Inputs!C6-(Inputs!C6*G3))*Inputs!C24)*Inputs!C11))*Inputs!C20))*Inputs!C18) + (((Inputs!C6*G3)+((Inputs!C6-(Inputs!C6*G3))*Inputs!C24))*Inputs!C19)))) -> 495.35225

Sheet Recommendations
A1: Recommendations (Practical, 500-User Stage)
A2: Priority | B2: Recommendation | C2: What to do | D2: Target / Why it matters
A3: 1 | B3: 1) Optimize activation before scaling traffic | C3: Focus on Signup → First export/tailor completion. Add onboarding checklist, template preview, and a clear “Tailor to this job” CTA in the editor. | D3: Target: Signup→First export 50–70%; reduce drop-offs with better error handling and progress UI.
A4: 2 | B4: 2) Protect margins with credit limits + caching | C4: Cap free credits, cap output length, cache identical generations, and prefer cheaper models for drafts; reserve premium model for final polish. | D4: Target: AI cost per active user <$0.20–$0.50; watch token spikes from long job descriptions.
A5: 3 | B5: 3) Pricing experiments (fast, measurable) | C5: A/B test $19 vs $24, and test a weekly plan (e.g., $7/week) for high-churn job seekers. Keep $9 one-time as impulse option. | D5: Goal: Improve revenue without harming conversion; watch refund rate (<2%).
A6: 4 | B6: 4) Convert exports into referrals | C6: Add subtle “Made with ResumeBuilder AI” referral link on free/watermarked exports; give both users extra credits. | D6: Goal: Reduce CAC; build organic loop.
A7: 5 | B7: 5) Channel focus (lowest CAC first) | C7: Start with SEO pages per role (“ATS resume for data analyst”), then short-form before/after content. Use paid ads only after conversion is stable. | D7: Rule: Only scale ads when LTV ≥ 3× CAC and payback < 2 months.
A8: 6 | B8: 6) KPI dashboard and weekly cost audit | C8: Track funnel + unit economics weekly: MAU, activation, conversion, AI cost/user, refunds, churn. | D8: Prevent silent margin erosion from token growth, retries, or prompt bloat.
A10: Suggested KPI Targets
A11: Activation (signup → first export): 50–70%
A12: Free → paid conversion (overall): 10–25%
A13: Monthly churn (subs): 8–20% (job seekers are naturally high)
A14: Refund rate: < 2%
A15: AI cost per active user: <$0.20–$0.50
A16: LTV : CAC ≥ 3× and payback < 2 months
